{
  "id": "11912",
  "title": "Дитяча настільна гра \"Вжик-вжик Липучки\" VT1302-21 від 3 років",
  "vendorCode": "VT1302-21",
  "price": "147",
  "old_price": "0",
  "available": true,
  "description_ua": "Барвиста, відмінно виконана і цікава гра настільна \"Вжик-вжик Липучки\" VT1302-21 Машинки - ідеальний, універсальний презент для дитини старше 12-ти місяців. Якщо Ви перебуваєте в пошуку цікавої іграшки, яка не тільки відверне малюка, але і посприяє розвитку важливих навичок, то цей чудовий комплект створений персонально для Вас. Ігровий розвиваючий комплект включає в себе 8 фігурок, 4 поля для гри, 8 жовтих липучок, 8 білих липучок, за допомогою яких малюк зможе самостійно або за допомогою дорослих уважно вивчати ігрові поля. Допоможіть своєму непосиді дізнатися нові назви різних дорожніх засобів, особливості, якими володіє кожна з них. В процесі гри Ваш малюк дізнається, навіщо для проїзду на мотоциклі обов'язково потрібен шолом, а також яку форму носить водій паровоза і багато іншого. Дізнавайтеся з малюком про все найцікавіше, зіставляючи деталі з ігровими полями за допомогою липучок, що посприяє розширенню кругозору та поповненню словникового запасу.",
  "categoryBaza_id": "82",
  "categoryBaza": "Настільні ігри",
  "categoryId": "221",
  "country_of_origin": "Україна",
  "pictureMY": [
    "13950.970.jpg",
    "13949.970.jpg"
  ],
  "myURL": "dityacha-nastilna-gra-vgik-vgik-lipuchki-vt1302-21-vid-3-rokivVT1302-21",
  "params": {
    "Вага товару": "0.155",
    "Габарити: довжина": "18.5",
    "Габарити: ширина": "4.5",
    "Габарити: висота": "18.5",
    "Стан": "нове",
    "Вікова група": "Від 3 років",
    "Матеріал": "картон",
    "Тип": "Настільна гра",
    "Колір": "Різнобарвний",
    "Упаковка": "Картонна коробка",
    "Вид": "Розвиваюча іграшка",
    "Вік": "Від 3-х років",
    "Гарантія": "14 днів",
    "Стать": "Унісекс",
    "Країна реєстрації бренду": "Україна",
    "Країна-виробник товару": "Україна"
  },
  "category_info": {
    "id": "82",
    "name": "Настільні ігри",
    "data_href": "./nastilni-ihry"
  },
  "url": "https://kiko-store.com.ua/nastilni-ihry/dityacha-nastilna-gra-vgik-vgik-lipuchki-vt1302-21-vid-3-rokivVT1302-21",
  "created_at": "2025-09-10T21:05:57.543Z",
  "updated_at": "2025-09-10T21:05:57.543Z"
}