{
  "id": "13380",
  "title": "Дитячий конструктор \"Юні-блок\" -60 70101, 60 великих деталей",
  "vendorCode": "70101",
  "price": "330",
  "old_price": "0",
  "available": true,
  "description_ua": "Барвистий конструктор \"Юні-блок\" -60 (паяний пакет) 70101 з великими деталями включає в себе квадратні блоки, прямокутні вузькі блоки, а також прямокутні довгі блоки, даху, і безліч інших деталей. У наборі Ваш малюк знайде скошені дахи, машинки, і навіть спеціальні траси для машинок. Якщо Ви шукали корисну іграшку для розвитку просторового мислення і уяви, то для малюків від 2-х років цей набір ідеально підійде. Гра не тільки розвиває у дитини мислення, увагу, посидючість, уяву, фантазію, дрібну і велику моторику, точність, а й позитивно впливає на координацію рухів. Деталі виготовлені з якісного, міцного і вологостійкого пластика, який не містить токсичних барвників і добавок. Іграшка абсолютно безпечна для Вашої дитини, підходить і для домашнього проведення часу, і для дитячого саду.",
  "categoryBaza_id": "53",
  "categoryBaza": "Дитячі конструктори",
  "categoryId": "95",
  "country_of_origin": "Україна",
  "pictureMY": [
    "16937.970.jpg"
  ],
  "myURL": "dityachiy-konstruktor-yuni-blok--60-70101-60-velikih-detaley70101",
  "params": {
    "Вага товару": "0.5",
    "Габарити: довжина": "40",
    "Габарити: ширина": "15",
    "Габарити: висота": "15",
    "Стан": "нове",
    "Вікова група": "Від 2 років",
    "Матеріал": "пластик",
    "Тип": "Конструктор",
    "Колір": "Різнобарвний",
    "Вік": "Від 2-х років",
    "Тип конструктора": "блоковий",
    "Стать": "Унісекс",
    "Країна реєстрації бренду": "Україна",
    "Країна-виробник товару": "Україна",
    "Кількість деталей": "60"
  },
  "category_info": {
    "id": "53",
    "name": "Дитячі конструктори",
    "data_href": "./konstruktory"
  },
  "url": "https://kiko-store.com.ua/konstruktory/dityachiy-konstruktor-yuni-blok--60-70101-60-velikih-detaley70101",
  "created_at": "2025-09-10T21:05:58.213Z",
  "updated_at": "2025-09-10T21:05:58.213Z"
}