{
  "id": "14449",
  "title": "Набір для творчості \"Тісто для ліплення\" Master Do\" Шеф-кухар Кондитер TMD-10-03U",
  "vendorCode": "TMD-10-03U",
  "price": "237",
  "old_price": "284",
  "available": true,
  "description_ua": "Тісто для ліплення \"Master-Do: Шеф-Кухар\" - це набір креативної творчості, розроблений і призначений для дітей і дорослих. З даним набором дитина зможе відчути себе справжнім шеф-кухарем кращого ресторану та здивувати всіх своїми кулінарними шедеврами. Морозиво, тістечко, кекси і навіть пончики... Заняття ліпленням допомагає розвинути уяву, творчі здібності і дрібну моторику рук. Комплектація: Тісто для ліплення (10 шт.), тісто для ліплення в баночках (2 шт.) кульковий пластилін (3 шт.), текстурайзер \"вафлі\", 2 стека, качалка, екструдер, вітрина для морозива, формочки (2 шт.), палички (4 шт.), інструкція",
  "categoryBaza_id": "74",
  "categoryBaza": "Набори для творчості",
  "categoryId": "1685",
  "country_of_origin": "Україна",
  "pictureMY": [
    "18994.970.jpg"
  ],
  "myURL": "nabir-dlya-tvorchosti-tisto-dlya-liplennya-master-do-shef-kuhar-konditer-tmd-10-03uTMD-10-03U",
  "params": {
    "Габарити: довжина": "20",
    "Габарити: ширина": "27",
    "Габарити: висота": "8",
    "Стан": "нове",
    "Вікова група": "Від 3 років",
    "Матеріал": "Комбінований",
    "Тип": "Пластилін",
    "Колір": "Різні кольори",
    "Упаковка": "Картонна коробка",
    "Вид": "Набір для творчості",
    "Вік": "Від 3-х років",
    "Гарантія": "14 днів",
    "Стать": "Унісекс",
    "Країна реєстрації бренду": "Україна",
    "Країна-виробник товару": "Україна",
    "Вага": "570.0 г"
  },
  "category_info": {
    "id": "74",
    "name": "Набори для творчості",
    "data_href": "./nabory-dlya-tvorchosti"
  },
  "url": "https://kiko-store.com.ua/nabory-dlya-tvorchosti/nabir-dlya-tvorchosti-tisto-dlya-liplennya-master-do-shef-kuhar-konditer-tmd-10-03uTMD-10-03U",
  "created_at": "2025-09-10T21:05:58.481Z",
  "updated_at": "2025-09-10T21:05:58.481Z"
}