{
  "id": "15485s28327",
  "title": "Настільна гра Шахи YT29A з шашками і нардами YT29B",
  "vendorCode": "YT29B",
  "price": "332",
  "old_price": "0",
  "available": true,
  "description_ua": "Шахи дерев'яні 3 в 1 YT29A-B універсальний комплект для гри в шахи, шашки та нарди з дошкою-футляром. У наборі: 1 коробка-поле, 2 кубика (кістки), 30 фішок для нард і шашок, 32 фігури для шахів. На вибір два колірних рішення дошки. І головне що завжди можна знайти ту гру яка буде цікава всім граючим і дорослим, і дітям. Всі три інтелектуальні логічні ігри не потребують реклами, вони пройшли багатовікове випробування часом, і гідно його витримали. При розумному підході, і хороших партнерах позитивний ефект від освоєння класичних настільних ігор гарантований. Чудовий подарунок для всієї родини. Набір компактний і зручний для транспортування. Виріб відповідає санітарно-технічним нормам і рекомендований для використання дітьми старше 3-х років.",
  "categoryBaza_id": "82",
  "categoryBaza": "Настільні ігри",
  "categoryId": "200",
  "country_of_origin": "",
  "pictureMY": [
    "21179.970.jpg"
  ],
  "myURL": "nastilna-gra-shahi-yt29a-z-shashkami-i-nardami--yt29bYT29B",
  "params": {
    "Вага товару": "0.5",
    "Габарити: довжина": "30",
    "Габарити: ширина": "15",
    "Габарити: висота": "4",
    "Стан": "нове",
    "Вікова група": "Від 6 років",
    "Матеріал": "Комбінований",
    "Тип": "Набори",
    "Колір": "Різнобарвний",
    "Упаковка": "Картонна коробка",
    "Вид": "Шахи, шашки, нарди",
    "Призначення": "Для двох",
    "Вік": "Від 6-ти років",
    "Жанр": "Логічні",
    "Гарантія": "14 днів",
    "Стать": "Унісекс",
    "Кількість гравців": "Для 2-х",
    "Країна реєстрації бренду": "Китай",
    "Найменування різновиду": "YT29B"
  },
  "category_info": {
    "id": "82",
    "name": "Настільні ігри",
    "data_href": "./nastilni-ihry"
  },
  "url": "https://kiko-store.com.ua/nastilni-ihry/nastilna-gra-shahi-yt29a-z-shashkami-i-nardami--yt29bYT29B",
  "created_at": "2025-09-10T21:05:57.088Z",
  "updated_at": "2025-09-10T21:05:57.088Z"
}