{
  "id": "20349",
  "title": "Дитяча книга Як полюбити павучка? 152329",
  "vendorCode": "152329",
  "price": "536",
  "old_price": "0",
  "available": true,
  "description_ua": "Маленька цікава паучінка, яку придумали Діана Амфт і Мартіна Матос, повертається, і не одна, а з друзями, родичами і новими враженнями! Тепер цілих чотири казки під однією обкладинкою! Ви дізнаєтеся, чому люди бояться павуків, побуваєте на павутину дні народження і почуєте цікаві історії про тварин далекої Африки, відвідайте ферму і познайомитеся з місцевими тваринами, а також разом з героями і іншими мешканцями лісу відчуєте радість від того, що в родині з'являється ще один дитина.",
  "categoryBaza_id": "279",
  "categoryBaza": "Дитячі книги",
  "categoryId": "571",
  "country_of_origin": "Україна",
  "pictureMY": [
    "35657.970.jpg",
    "35654.970.jpg",
    "35655.970.jpg",
    "35656.970.jpg"
  ],
  "myURL": "dityacha-kniga-yak-polyubiti-pavuchka-152329152329",
  "params": {
    "Вага товару": "0.45",
    "Габарити: довжина": "24.8",
    "Габарити: ширина": "21",
    "Габарити: висота": "3",
    "Стан": "нове",
    "Вікова група": "Від 3 років",
    "Тематика": "Загальний розвиток",
    "Вік": "Від 3-х років",
    "Жанр": "Оповідання",
    "Стать": "Унісекс",
    "Країна реєстрації бренду": "Україна",
    "Країна-виробник товару": "Україна",
    "Видавництво": "Час майстрів",
    "Розділ": "Художні книги",
    "Кількість сторінок": "104",
    "Обладинка": "твердий",
    "Папір": "Офсетна",
    "Формат": "248х210",
    "Мова видання": "Українська",
    "Тип книги": "паперова",
    "Автор": "Діана Амфт",
    "Рік видавництва": "2018"
  },
  "category_info": {
    "id": "279",
    "name": "Дитячі книги",
    "data_href": "./dytyachi-knyhy"
  },
  "url": "https://kiko-store.com.ua/dytyachi-knyhy/dityacha-kniga-yak-polyubiti-pavuchka-152329152329",
  "created_at": "2025-09-10T21:05:56.850Z",
  "updated_at": "2025-09-10T21:05:56.850Z"
}