{
  "id": "24866s32316",
  "title": "Дитячий набір \"Лопатка мала з дерев'яною ручкою\" ТехноК 2896TXK, 65 см Червоний",
  "vendorCode": "2896TXK(Red)",
  "price": "62",
  "old_price": "0",
  "available": true,
  "description_ua": "Уявити себе справжнім садівником дитині допоможе незамінний інструмент для саду і городу - лопата з великою дерев'яною ручкою. Гра малюка стане реалістичною і допоможе Вашій дитині відчути себе дорослішим. Підходить для піску і снігу. Іграшка виготовлена з міцного і якісного пластика без запаху і без гострих країв.",
  "categoryBaza_id": "146",
  "categoryBaza": "Іграшки для вулиці та дитячого майданчика",
  "categoryId": "479",
  "country_of_origin": "Україна",
  "pictureMY": [
    "48239.970.jpg"
  ],
  "myURL": "dityachiy-nabir-lopatka-mala-z-derevyyanoyu-ruchkoyu-tehnok-2896txk-65-sm--chervoniy2896TXKRed",
  "params": {
    "Вага товару": "0.19",
    "Габарити: довжина": "65",
    "Габарити: ширина": "19",
    "Габарити: висота": "8",
    "Стан": "нове",
    "Вікова група": "Від 1 року",
    "Матеріал": "Дерево /пластик",
    "Тип": "Лопата",
    "Колір": "Різні кольори",
    "Упаковка": "Без упаковки",
    "Вид": "Один предмет",
    "Вік": "Від 12 міс",
    "Гарантія": "14 днів",
    "Стать": "Унісекс",
    "Країна реєстрації бренду": "Україна",
    "Країна-виробник товару": "Україна",
    "Розмір, см": "19х8х65",
    "Найменування різновиду": "Червоний"
  },
  "category_info": {
    "id": "146",
    "name": "Іграшки для вулиці та дитячого майданчика",
    "data_href": "./ihrashky-dlya-vulytsi"
  },
  "url": "https://kiko-store.com.ua/ihrashky-dlya-vulytsi/dityachiy-nabir-lopatka-mala-z-derevyyanoyu-ruchkoyu-tehnok-2896txk-65-sm--chervoniy2896TXKRed",
  "created_at": "2025-09-10T21:05:57.690Z",
  "updated_at": "2025-09-10T21:05:57.690Z"
}