{
  "id": "24956s32464",
  "title": "Ігрова фігурка трансформер Bambi CX1625 Динозавр Коричневий",
  "vendorCode": "CX1625(Brown)",
  "price": "243",
  "old_price": "0",
  "available": true,
  "description_ua": "Дивовижний рухливий динозавр-трансформер стане чудовим доповненням до колекції іграшок вашого малюка. Він легко перетворюється на робота з лапами, що рухаються, і звуковими ефектами. Виготовлений із безпечних матеріалів",
  "categoryBaza_id": "44",
  "categoryBaza": "Іграшки для хлопчиків",
  "categoryId": "52",
  "country_of_origin": "Китай",
  "pictureMY": [
    "48786.970.jpg",
    "48786.970.jpg"
  ],
  "myURL": "igrova-figurka-transformer-bambi-cx1625-dinozavr--korichneviyCX1625Brown",
  "params": {
    "Габарити: довжина": "5",
    "Габарити: ширина": "5",
    "Габарити: висота": "7",
    "Стан": "нове",
    "Вікова група": "Від 3 років",
    "Матеріал": "пластик",
    "Тип": "трансформер",
    "Колір": "Різні кольори",
    "Упаковка": "Без упаковки",
    "Вид": "Динозаври",
    "Вік": "Від 3-х років",
    "Гарантія": "14 днів",
    "Стать": "Унісекс",
    "Країна реєстрації бренду": "Китай",
    "Країна-виробник товару": "Китай",
    "Розмір, см": "5х7х5 см",
    "Найменування різновиду": "Коричневий"
  },
  "category_info": {
    "id": "44",
    "name": "Іграшки для хлопчиків",
    "data_href": "./dlya-khlopchykiv"
  },
  "url": "https://kiko-store.com.ua/dlya-khlopchykiv/igrova-figurka-transformer-bambi-cx1625-dinozavr--korichneviyCX1625Brown",
  "created_at": "2025-09-10T21:05:58.742Z",
  "updated_at": "2025-09-10T21:05:58.742Z"
}