{
  "id": "26102",
  "title": "Дитячий іграшковий мікрофон 846BS зі світлом та звуком",
  "vendorCode": "846BS",
  "price": "309",
  "old_price": "0",
  "available": true,
  "description_ua": "Мікрофон 846BS виготовлений з яскравої пластмаси високої якості. На мікрофончику 846BS розташовано кілька різнокольорових кнопочок, натискаючи на які можна буде вибрати відповідні функції. Рекомендується для найменших дітей від 18 місяців. Мікрофон упакований у коробочку розміром 14х7, 5х25 сантиметрів. Вік: від 18 міс.",
  "categoryBaza_id": "17",
  "categoryBaza": "Іграшки для малюків",
  "categoryId": "23",
  "country_of_origin": "Китай",
  "pictureMY": [
    "88258.970.jpg",
    "51885.970.jpg"
  ],
  "myURL": "dityachiy-igrashkoviy-mikrofon-846bs-zi-svitlom-ta-zvukom846BS",
  "params": {
    "Габарити: довжина": "25",
    "Габарити: ширина": "14",
    "Габарити: висота": "7.5",
    "Стан": "нове",
    "Вікова група": "Від 1,5 років",
    "Особливості": "Світлові ефекти | Звукові ефекти",
    "Матеріал": "пластик",
    "Тип": "МІкрофон",
    "Колір": "Різні кольори",
    "Упаковка": "Планшет",
    "Вид": "Розвиваюча іграшка",
    "Вік": "Від 18 міс",
    "Гарантія": "14 днів",
    "Стать": "Унісекс",
    "Країна реєстрації бренду": "Китай",
    "Країна-виробник товару": "Китай"
  },
  "category_info": {
    "id": "17",
    "name": "Іграшки для малюків",
    "data_href": "./dlya-malyukiv"
  },
  "url": "https://kiko-store.com.ua/dlya-malyukiv/dityachiy-igrashkoviy-mikrofon-846bs-zi-svitlom-ta-zvukom846BS",
  "created_at": "2025-09-10T21:05:58.777Z",
  "updated_at": "2025-09-10T21:05:58.777Z"
}