{
  "id": "29860s39191",
  "title": "Скейт \"Пенні борд\" Bambi SC17067 колеса PVC, 55 см Вид 4",
  "vendorCode": "SC17067-4",
  "price": "592",
  "old_price": "0",
  "available": true,
  "description_ua": "Пенні борд арт. SC17067 - це компактна скейтборд-дошка, яка має металеві кріплення і колеса з PVC матеріалу. Розміри дошки становлять 55 см в довжину і 13 см в ширину. Ця дошка є дуже легкою та маневреною, що дозволяє легко керувати і виконувати різноманітні трюки. Також вона має стильний дизайн, який може задовольнити різний смак любителів скейтбордингу. Загалом, ця дошка є чудовим вибором для тих, хто шукає зручне і якісне скейтборд-обладнання.",
  "categoryBaza_id": "79",
  "categoryBaza": "Дитячі транспортні засоби",
  "categoryId": "153",
  "country_of_origin": "Китай",
  "pictureMY": [
    "65721.970.jpg"
  ],
  "myURL": "skeyt-penni-bord-bambi-sc17067-kolesa-pvc-55-sm-vid-4SC17067-4",
  "params": {
    "Габарити: довжина": "55",
    "Габарити: ширина": "13",
    "Габарити: висота": "9",
    "Стан": "нове",
    "Вікова група": "Від 6 років",
    "Особливості": "Світлові ефекти",
    "Матеріал": "Комбінований",
    "Тип": "Скейт",
    "Колір": "червоний",
    "Упаковка": "Поліетиленовий пакет",
    "Вид": "транспорт",
    "Вік": "Від 6-ти років",
    "Гарантія": "14 днів",
    "Стать": "Унісекс",
    "Країна реєстрації бренду": "Китай",
    "Країна-виробник товару": "Китай",
    "Найменування різновиду": "Вид 4"
  },
  "category_info": {
    "id": "79",
    "name": "Дитячі транспортні засоби",
    "data_href": "./transportni-zasoby"
  },
  "url": "https://kiko-store.com.ua/transportni-zasoby/skeyt-penni-bord-bambi-sc17067-kolesa-pvc-55-sm-vid-4SC17067-4",
  "created_at": "2025-08-18T11:50:11.879Z",
  "updated_at": "2025-08-18T11:50:11.879Z"
}