{
  "id": "34728",
  "title": "Конструктор динозавр Giantraptor WEN SHENG 5703 механізований",
  "vendorCode": "5703",
  "price": "499",
  "old_price": "599",
  "available": true,
  "description_ua": "Конструктор із серії \"Armored dinosaur models\" від WEN SHENG. Можна зібрати роботизовану модель динозавра GIANTRAPTOR . Модель оснащена мотором і може ходити. Деталізований текстури дизайн з рухомими елементами. Розмір коробки: 39х31х9 см.",
  "categoryBaza_id": "53",
  "categoryBaza": "Дитячі конструктори",
  "categoryId": "573",
  "country_of_origin": "Китай",
  "pictureMY": [
    "77012.970.jpg"
  ],
  "myURL": "konstruktor-dinozavr-giantraptor-wen-sheng-5703-mehanizovaniy5703",
  "params": {
    "Вага товару": "1",
    "Габарити: довжина": "33",
    "Габарити: ширина": "9.5",
    "Габарити: висота": "23",
    "Стан": "нове",
    "Вікова група": "Від 8 років",
    "Матеріал": "пластик",
    "Тип": "Конструктор",
    "Колір": "червоний",
    "Упаковка": "Картонна коробка",
    "Вид": "Електронний конструктор",
    "Вік": "Від 8-ми років",
    "Гарантія": "14 днів",
    "Стать": "Унісекс",
    "Живлення іграшки": "1 батарейка типу ААА (у комплект не входить)",
    "Країна реєстрації бренду": "Китай",
    "Країна-виробник товару": "Китай"
  },
  "category_info": {
    "id": "53",
    "name": "Дитячі конструктори",
    "data_href": "./konstruktory"
  },
  "url": "https://kiko-store.com.ua/konstruktory/konstruktor-dinozavr-giantraptor-wen-sheng-5703-mehanizovaniy5703",
  "created_at": "2025-09-10T21:05:58.947Z",
  "updated_at": "2025-09-10T21:05:58.947Z"
}