{
  "id": "41243",
  "title": "Електронний конструктор \"Світло та колір RGB\" DOKA D70700 зі світлом",
  "vendorCode": "D70700",
  "price": "1395",
  "old_price": "1674",
  "available": true,
  "description_ua": "Конструктор електронний DOKA - 'СВІТЛО ТА КОЛІР RGB' безсумнівно сподобається юним дослідникам! Кожен з Вас малював фарбами та пробував їх змішувати, щоб отримати потрібний колір. Чим більше фарб, тим більше відтінків. Але мало хто мав досвід по змішуванню світла. А там результат не завжди очікуваний. Якщо Ви змішаєте червону, зелену і синю фарби, то ніколи не отримаєте білого. А змішуючи світло - це можливо! Важко собі уявити, що вся гама кольорів, яку Ви бачите на екранах смартфонів, моніторах комп'ютерів, телевізорах, рекламних щитах, створюється за допомогою всього трьох кольорів - червоного, синього та зеленого! І цей набір дозволить Вам переконатися в цьому. Цей набір чудово підійде як для індивідуальних занять в спокійній домашній обстановці, так і для занять додаткової освіти. У комплект входить: 60 деталей посібник, за допомогою якого дитина зможе створити 24 світлові схеми. Такий електронний конструктор розвиває в дитині: творче мислення, увагу, логіку, пам'ять. Для роботи конструктора необхідні 2 батарейки типу АА. Рекомендовано для дітей віком від 8 років.",
  "categoryBaza_id": "53",
  "categoryBaza": "Дитячі конструктори",
  "categoryId": "573",
  "country_of_origin": "Китай",
  "pictureMY": [
    "87557.970.jpg",
    "87558.970.jpg",
    "87559.970.jpg",
    "87560.970.jpg",
    "87561.970.jpg",
    "87562.970.jpg"
  ],
  "myURL": "elektronniy-konstruktor-svitlo-ta-kolir-rgb-doka-d70700-zi-svitlomD70700",
  "params": {
    "Стан": "нове",
    "Вікова група": "Від 8 років",
    "Особливості": "Світлові ефекти",
    "Матеріал": "Метал /пластик",
    "Тип": "Електро-конструктор",
    "Колір": "Різні кольори",
    "Упаковка": "Картонна коробка",
    "Габарити: довжина": "40",
    "Габарити: ширина": "20",
    "Габарити: висота": "2",
    "Вік": "Від 8-ми років",
    "Гарантія": "14 днів",
    "Стать": "Для хлопчиків",
    "Живлення іграшки": "2 батарейки типу АА (у комплект не входять)",
    "Країна реєстрації бренду": "Китай",
    "Країна-виробник товару": "Китай"
  },
  "category_info": {
    "id": "53",
    "name": "Дитячі конструктори",
    "data_href": "./konstruktory"
  },
  "url": "https://kiko-store.com.ua/konstruktory/elektronniy-konstruktor-svitlo-ta-kolir-rgb-doka-d70700-zi-svitlomD70700",
  "created_at": "2025-09-10T21:05:58.539Z",
  "updated_at": "2025-09-10T21:05:58.539Z"
}