{
  "id": "41551",
  "title": "Ігровий набір Сонечко Ніко W2 Bubiloons 85541 фігурка, аксесуари, кульки",
  "vendorCode": "85541",
  "price": "375",
  "old_price": "0",
  "available": true,
  "description_ua": "Ігровий набір BUBILOONS – СОНЕЧКО НІКО – це ідеальний подарунок для творчих та креативних дітей! Ви познайомитеся з милими та дивовижними тваринами, які надувають барвисті кульки. Це ж не просто колекційна іграшка, а цілий набір для веселощів! BUBILOONS – справжній сюрприз! Адже у наборі є кульки, які Ваш герой може надувати! Необхідно вставити паличку-трубочку однією стороною до рота героя, а до іншої сторони прикріпити одну з кульок. Здавлюйте голову героя з двох сторін, і дивіться, як надувається кулька! Просто неймовірно! Кожен герой має свій особливий аксесуар. З'єднайте кульки з предметами, щоб створити супер круті аксесуари. У колекції 10 різних героїв. Зберіть їх усіх для веселішої гри! У наборі: 1 фігурка. Аксесуари. Надувні кульки. Рекомендовано для дітей віком від 5 років.",
  "categoryBaza_id": "30",
  "categoryBaza": "Іграшки фігурки тварин",
  "categoryId": "30",
  "country_of_origin": "Китай",
  "pictureMY": [
    "88217.970.jpg",
    "88218.970.jpg",
    "88219.970.jpg",
    "88220.970.jpg",
    "88221.970.jpg"
  ],
  "myURL": "igroviy-nabir-sonechko-niko-w2-bubiloons-85541-figurka-aksesuari-kulki85541",
  "params": {
    "Стан": "нове",
    "Вікова група": "Від 5 років",
    "Матеріал": "пластик",
    "Тип": "Фігурка героїв",
    "Колір": "Різні кольори",
    "Упаковка": "Демонстраційно-відкрита",
    "Вік": "Від 5-ти років",
    "Гарантія": "14 днів",
    "Стать": "Для дівчаток",
    "Країна реєстрації бренду": "Іспанія",
    "Країна-виробник товару": "Китай"
  },
  "category_info": {
    "id": "30",
    "name": "Іграшки фігурки тварин",
    "data_href": "./fihurky-tvaryn"
  },
  "url": "https://kiko-store.com.ua/fihurky-tvaryn/igroviy-nabir-sonechko-niko-w2-bubiloons-85541-figurka-aksesuari-kulki85541",
  "created_at": "2025-09-10T21:05:57.990Z",
  "updated_at": "2025-09-10T21:05:57.990Z"
}