{
  "id": "46169",
  "title": "М'яка дитяча іграшка антистрес \"JELLY MONSTER\" JM-001(White) білий 9 см",
  "vendorCode": "JM-001(White)",
  "price": "117",
  "old_price": "0",
  "available": true,
  "description_ua": "Кумедний пухнастик \"Jelly Monster\" - це м'яка іграшка у вигляді монстрика. Він приємний і м'який на дотик, з функцією антистресу. Натискаючи на іграшку, вилазить прозора куля з орбізами усередині. Розмір іграшки: 9 - 9 см;",
  "categoryBaza_id": "83",
  "categoryBaza": "М'які іграшки",
  "categoryId": "626",
  "country_of_origin": "Китай",
  "pictureMY": [
    "97681.970.jpg"
  ],
  "myURL": "myyaka-dityacha-igrashka-antistres-jelly-monster-jm-001white-biliy-9-smJM-001White",
  "params": {
    "Габарити: довжина": "9",
    "Габарити: ширина": "5",
    "Габарити: висота": "9",
    "Стан": "нове",
    "Вікова група": "Від 3 років",
    "Матеріал": "плюш",
    "Тип": "Антистрес",
    "Колір": "білий",
    "Упаковка": "Без упаковки",
    "Вид": "М'які іграшки",
    "Вік": "Від 3-х років",
    "Гарантія": "Обміну та поверненню не підлягає",
    "Стать": "Унісекс",
    "Країна реєстрації бренду": "Китай",
    "Країна-виробник товару": "Китай",
    "Тип М'якої іграшки": "Інші",
    "Розмір, см": "9"
  },
  "category_info": {
    "id": "83",
    "name": "М'які іграшки",
    "data_href": "./myaki-igrashky"
  },
  "url": "https://kiko-store.com.ua/myaki-igrashky/myyaka-dityacha-igrashka-antistres-jelly-monster-jm-001white-biliy-9-smJM-001White",
  "created_at": "2025-09-10T21:05:57.788Z",
  "updated_at": "2025-09-10T21:05:57.788Z"
}