{
  "id": "46840",
  "title": "Антистрес Сквіш \"М'який Єдиноріг\" SKU-505 яскраве забарвлення",
  "vendorCode": "SKU-505",
  "price": "55",
  "old_price": "0",
  "available": true,
  "description_ua": "Антистрес іграшка \"Єдиноріг\" - це м'яка і забавна іграшка, створена у вигляді маленького поні з яскравим, райдужним забарвленням. Іграшка виконана з м'якими плавними лініями та округлими формами, що робить її приємною на дотик та візуально привабливою. Яскраві кольори радують око, а ніжний матеріал легко стискується і швидко відновлює форму, допомагаючи зняти напругу та стрес. Іграшка компактна та легка, ідеально підходить для використання в будь-яких умовах – на робочому місці, вдома чи в дорозі. Приємна тактильна текстура та весела форма піднімають настрій та допомагають розслабитися.",
  "categoryBaza_id": "488",
  "categoryBaza": "Іграшки антистрес",
  "categoryId": "490",
  "country_of_origin": "Китай",
  "pictureMY": [
    "98935.970.jpg"
  ],
  "myURL": "antistres-skvish-myyakiy-edinorig-sku-505-yaskrave-zabarvlennyaSKU-505",
  "params": {
    "Габарити: довжина": "8",
    "Габарити: ширина": "1.5",
    "Габарити: висота": "8",
    "Стан": "нове",
    "Вікова група": "Від 3 років",
    "Матеріал": "Комбінований",
    "Тип": "Антистрес",
    "Колір": "рожевий",
    "Упаковка": "Поліетиленовий пакет",
    "Вид": "Розважальні",
    "Вік": "Від 3-х років",
    "Гарантія": "14 днів",
    "Стать": "Для дівчаток",
    "Країна реєстрації бренду": "Китай",
    "Країна-виробник товару": "Китай"
  },
  "category_info": {
    "id": "488",
    "name": "Іграшки антистрес",
    "data_href": "./ihrashky-antystres"
  },
  "url": "https://kiko-store.com.ua/ihrashky-antystres/antistres-skvish-myyakiy-edinorig-sku-505-yaskrave-zabarvlennyaSKU-505",
  "created_at": "2025-09-10T21:05:57.317Z",
  "updated_at": "2025-09-10T21:05:57.317Z"
}