{
  "id": "47728",
  "title": "Дитяча модель Мотоцикла \"Ducati SuperSport 900\" Bburago 18-51030-14 масштаб 1:18",
  "vendorCode": "18-51030-14",
  "price": "330",
  "old_price": "0",
  "available": true,
  "description_ua": "Модель мотоцикла Bburago стане відмінним подарунком як для маленького мотолюбителя, так і дорослого шанувальника автомобілів світового автопрому. В асортименті присутні моделі мотоциклів різних класів: спортивні, родстери, гоночні та інші. Зібравши колекцію мотоциклів, дитина зможе влаштувати справжні перегони з їх участю! Автомоделі та моделі мотоциклів Bburago допоможуть розвинути у дитини: сприйняття простору, світогляд, вміння грати і колекціонувати. Масштаб - 1:18. Рекомендовано для дітей віком від 3 років.",
  "categoryBaza_id": "44",
  "categoryBaza": "Іграшки для хлопчиків",
  "categoryId": "340",
  "country_of_origin": "Китай",
  "pictureMY": [
    "101385.970.jpg"
  ],
  "myURL": "dityacha-model-mototsikla-ducati-supersport-900-bburago-18-51030-14-masshtab-11818-51030-14",
  "params": {
    "Вага товару": "0.1",
    "Габарити: довжина": "17",
    "Габарити: ширина": "11",
    "Габарити: висота": "7",
    "Стан": "нове",
    "Вікова група": "Від 3 років",
    "Ширина": "11",
    "Висота": "7",
    "Довжина": "17",
    "Матеріал": "пластик",
    "Тип": "Мотоцикл",
    "Колір": "Різні кольори",
    "Упаковка": "Демонстраційно-відкрита",
    "Вид": "транспорт",
    "Вік": "Від 3-х років",
    "Гарантія": "14 днів",
    "Стать": "Для хлопчиків",
    "Країна реєстрації бренду": "Італія",
    "Країна-виробник товару": "Китай",
    "Марка": "Ducati"
  },
  "category_info": {
    "id": "44",
    "name": "Іграшки для хлопчиків",
    "data_href": "./dlya-khlopchykiv"
  },
  "url": "https://kiko-store.com.ua/dlya-khlopchykiv/dityacha-model-mototsikla-ducati-supersport-900-bburago-18-51030-14-masshtab-11818-51030-14",
  "created_at": "2025-09-10T21:05:57.261Z",
  "updated_at": "2025-09-10T21:05:57.261Z"
}