{
  "id": "48330",
  "title": "Дерев’яний дитячий пазл 4в1 \"Свійські тварини\" Puz-75595, 80 елементів",
  "vendorCode": "Puz-75595",
  "price": "345",
  "old_price": "0",
  "available": true,
  "description_ua": "<p>Дерев'яна розвиваюча іграшка-пазл \"Свійські тварини 4в1\" захопить увагу малюка завдяки яскравим кольорам, милим зображенням свійських тваринок. У комплекті знаходяться 4 пазли з малюнками ягнятка, віслючка, поросятка та індички, які легко впізнаються дітьми. </p> <p>Еко-пазл безпечний для малюків, оскільки при виготовленні використовуються лише натуральні матеріали. Діти залюбки складатимуть ці веселі пазли самотужки чи з допомогою дорослих.</p>",
  "categoryBaza_id": "1",
  "categoryBaza": "Дерев'яні іграшки",
  "categoryId": "335",
  "country_of_origin": "Україна",
  "pictureMY": [
    "102822.970.jpg",
    "102825.970.jpg",
    "102823.970.jpg",
    "102824.970.jpg",
    "102826.970.jpg"
  ],
  "myURL": "derevyaniy-dityachiy-pazl-4v1-sviyski-tvarini-puz-75595-80-elementivPuz-75595",
  "params": {
    "Стан": "нове",
    "Вікова група": "Від 3 років",
    "Матеріал": "дерево",
    "Колір": "Різні кольори",
    "Упаковка": "Коробка",
    "Вид": "Пазли",
    "Вік": "Від 3-х років",
    "Гарантія": "14 днів",
    "Стать": "Унісекс",
    "Країна реєстрації бренду": "Україна",
    "Країна-виробник товару": "Україна"
  },
  "category_info": {
    "id": "1",
    "name": "Дерев'яні іграшки",
    "data_href": "./derevyani-ihrashky"
  },
  "url": "https://kiko-store.com.ua/derevyani-ihrashky/derevyaniy-dityachiy-pazl-4v1-sviyski-tvarini-puz-75595-80-elementivPuz-75595",
  "created_at": "2025-09-10T21:05:57.132Z",
  "updated_at": "2025-09-10T21:05:57.132Z"
}