{
  "id": "48349",
  "title": "Настільна гра \"Хрестики-нолики\" Арт-13909, 11 елементів",
  "vendorCode": "Арт-13909",
  "price": "140",
  "old_price": "0",
  "available": true,
  "description_ua": "Захоплююча гра \"Хрестики-нолики\" для дітей дозволить вам цікаво проводити час з малюком. Прості правила та водночас стрімкий виграш - запорука популярності цієї парної гри. Грати в неї можна протягом всього дитинства - спершу дитина може складати її як пазл, а потім змагатися з однолітками. Іграшка розвиватиме кмітливість та логічне мислення.",
  "categoryBaza_id": "82",
  "categoryBaza": "Настільні ігри",
  "categoryId": "229",
  "country_of_origin": "Україна",
  "pictureMY": [
    "102894.970.jpg",
    "102895.970.jpg",
    "102896.970.jpg"
  ],
  "myURL": "nastilna-gra-hrestiki-noliki-art-13909-11-elementiv-13909",
  "params": {
    "Габарити: довжина": "13",
    "Габарити: ширина": "13",
    "Габарити: висота": "1",
    "Стан": "нове",
    "Вікова група": "Від 3 років",
    "Мови": "Мовонезалежна",
    "Матеріал": "дерево",
    "Тип": "Настільна гра",
    "Колір": "Різні кольори",
    "Упаковка": "Картонна коробка",
    "Вид": "Настільна гра",
    "Тематика": "Загальний розвиток",
    "Призначення": "Для двох",
    "Вік": "Від 3-х років",
    "Жанр": "Логічні",
    "Гарантія": "14 днів",
    "Стать": "Унісекс",
    "Час гри": "5-15 хвилин",
    "Кількість гравців": "Для 2-х",
    "Країна реєстрації бренду": "Україна",
    "Країна-виробник товару": "Україна"
  },
  "category_info": {
    "id": "82",
    "name": "Настільні ігри",
    "data_href": "./nastilni-ihry"
  },
  "url": "https://kiko-store.com.ua/nastilni-ihry/nastilna-gra-hrestiki-noliki-art-13909-11-elementiv-13909",
  "created_at": "2025-08-18T11:50:10.303Z",
  "updated_at": "2025-08-18T11:50:10.303Z"
}